git_find_repos.py
git_find_repos-2.1.0.dist-info/LICENSE
git_find_repos-2.1.0.dist-info/METADATA
git_find_repos-2.1.0.dist-info/WHEEL
git_find_repos-2.1.0.dist-info/entry_points.txt
git_find_repos-2.1.0.dist-info/top_level.txt
git_find_repos-2.1.0.dist-info/RECORD
