Metadata-Version: 2.1
Name: git-find-repos
Version: 2.1.0
Summary: CLI tool to find git repositories.
Home-page: https://github.com/acroz/git-find-repos
Author: Andrew Crozier
Author-email: wacrozier@gmail.com
License: MIT
Project-URL: GitHub, https://github.com/acroz/git-find-repos
Platform: UNKNOWN
